tspace/__init__.py
tspace/_modidx.py
tspace/avatar.py
tspace/core.py
tspace/sandbox.py
tspace/utils.py
tspace/agent/__init__.py
tspace/agent/ddpg.py
tspace/agent/dpg.py
tspace/agent/rdpg/__init__.py
tspace/agent/rdpg/rdpg.py
tspace/agent/rdpg/seq_actor.py
tspace/agent/rdpg/seq_critic.py
tspace/agent/utils/__init__.py
tspace/agent/utils/hyperparams.py
tspace/agent/utils/ou_action_noise.py
tspace/config/__init__.py
tspace/config/db.py
tspace/config/drivers.py
tspace/config/messengers.py
tspace/config/utils.py
tspace/config/vcu.py
tspace/config/vehicles.py
tspace/config/remotecan/__init__.py
tspace/config/remotecan/exceptions.py
tspace/conn/__init__.py
tspace/conn/remote_can_client.py
tspace/conn/remotecan.py
tspace/conn/tbox.py
tspace/conn/tcp.py
tspace/conn/udp.py
tspace/conn/remotecan/__init__.py
tspace/conn/remotecan/exceptions.py
tspace/data/__init__.py
tspace/data/core.py
tspace/data/location.py
tspace/data/time.py
tspace/data/external/__init__.py
tspace/data/external/numpy_utils.py
tspace/data/external/pandas_utils.py
tspace/dataflow/__init__.py
tspace/dataflow/cloud.py
tspace/dataflow/consumer.py
tspace/dataflow/cruncher.py
tspace/dataflow/kvaser.py
tspace/dataflow/producer.py
tspace/dataflow/vehicle_interface.py
tspace/dataflow/filter/__init__.py
tspace/dataflow/filter/filter.py
tspace/dataflow/filter/hetero.py
tspace/dataflow/filter/homo.py
tspace/dataflow/pipeline/__init__.py
tspace/dataflow/pipeline/deque.py
tspace/dataflow/pipeline/queue.py
tspace/storage/__init__.py
tspace/storage/buffer/__init__.py
tspace/storage/buffer/buffer.py
tspace/storage/buffer/dask.py
tspace/storage/buffer/mongo.py
tspace/storage/pool/__init__.py
tspace/storage/pool/dask.py
tspace/storage/pool/mongo.py
tspace/storage/pool/parquet.py
tspace/storage/pool/pool.py
tspace/storage/pool/avro/__init__.py
tspace/storage/pool/avro/avro.py
tspace/storage/pool/avro/schema.py
tspace/system/__init__.py
tspace/system/decorator.py
tspace/system/exception.py
tspace/system/graceful_killer.py
tspace-0.0.1.dist-info/LICENSE
tspace-0.0.1.dist-info/METADATA
tspace-0.0.1.dist-info/WHEEL
tspace-0.0.1.dist-info/entry_points.txt
tspace-0.0.1.dist-info/top_level.txt
tspace-0.0.1.dist-info/RECORD
