Metadata-Version: 2.1
Name: tspace
Version: 0.0.1
Summary: io interface
Home-page: https://github.com/Binjian/tspace
Author: binjian xin
Author-email: binjian.xin@hotmail.com
License: Apache Software License 2.0
Keywords: nbdev jupyter notebook python
Classifier: Development Status :: 4 - Beta
Classifier: Intended Audience :: Developers
Classifier: Natural Language :: English
Classifier: Programming Language :: Python :: 3.11
Classifier: License :: OSI Approved :: Apache Software License
Requires-Python: >=3.11
License-File: LICENSE
Requires-Dist: fastcore
Requires-Dist: pandas
Requires-Dist: numpy
Requires-Dist: pydantic
Requires-Dist: pyarrow
Requires-Dist: ordered-set
Requires-Dist: black[jupyter]
Requires-Dist: ruff
Requires-Dist: mypy
Requires-Dist: pylint
Requires-Dist: typing-inspect
Requires-Dist: typeguard
Requires-Dist: dacite
Requires-Dist: poetry
Requires-Dist: tensorflow
Requires-Dist: tensorflow-estimator
Requires-Dist: tensorflow-probability
Requires-Dist: tensorboard
Requires-Dist: flatbuffers
Requires-Dist: keras
Requires-Dist: python-json-logger
Requires-Dist: plotly
Requires-Dist: Pillow
Requires-Dist: opt-einsum
Requires-Dist: jupyterlab
Requires-Dist: notebook
Requires-Dist: scipy
Requires-Dist: seaborn
Requires-Dist: scikit-learn
Requires-Dist: matplotlib
Requires-Dist: pytest
Requires-Dist: reportlab
Requires-Dist: pymongo
Requires-Dist: fastavro
Requires-Dist: gitpython
Requires-Dist: jupytext
Requires-Dist: tqdm
Requires-Dist: pandas-stubs
Requires-Dist: nbstripout
Requires-Dist: nbdev
Requires-Dist: matplotlib-stubs
Requires-Dist: dask
Requires-Dist: poetry2conda
Requires-Dist: cutelog
Requires-Dist: pdoc3
Requires-Dist: itikz
Provides-Extra: dev
